pyopversion/__init__.py
pyopversion/base.py
pyopversion/consts.py
pyopversion/container.py
pyopversion/exceptions.py
pyopversion/local.py
pyopversion/opio.py
pyopversion/pypi.py
pyopversion/supervisor.py
pyopversion/version.py
pyopversion-3.5.0.dist-info/LICENSE
pyopversion-3.5.0.dist-info/METADATA
pyopversion-3.5.0.dist-info/WHEEL
pyopversion-3.5.0.dist-info/top_level.txt
pyopversion-3.5.0.dist-info/RECORD
